{"id": "2e378b92-c4da-4cac-ac93-db14c67fe0e8", "schema": "https://metadata.datadrivendiscovery.org/schemas/v0/pipeline.json", "created": "2019-04-24T19:15:03.658765Z", "context": "TESTING", "inputs": [{"name": "inputs"}], "outputs": [{"data": "steps.0.produce", "name": "output predictions"}], "steps": [{"type": "PRIMITIVE", "primitive": {"id": "d351fcf8-5d6c-48d4-8bf6-a56fe11e62d6", "version": "1.0.2", "python_path": "d3m.primitives.time_series_classification.shapelet_learning.Shallot", "name": "shallot"}, "arguments": {"inputs": {"type": "CONTAINER", "data": "inputs.0"}, "outputs": {"type": "CONTAINER", "data": "inputs.0"}}, "outputs": [{"id": "produce"}], "hyperparams": {"epochs": {"type": "VALUE", "data": 10000}, "learning_rate": {"type": "VALUE", "data": 0.001}}}]}
